MANIFEST.in
README.md
setup.py
lasotuvi_django/__init__.py
lasotuvi_django/apps.py
lasotuvi_django/tests.py
lasotuvi_django/urls.py
lasotuvi_django/utils.py
lasotuvi_django/views.py
lasotuvi_django/static/client.js
lasotuvi_django/static/html2canvas.js
lasotuvi_django/static/jquery.min.js
lasotuvi_django/static/jsrender.min.js
lasotuvi_django/static/lstv.js
lasotuvi_django/static/simpleserver
lasotuvi_django/static/style.css
lasotuvi_django/static/texture.jpg
lasotuvi_django/static/zebra_tooltips.js
lasotuvi_django/templates/index.html
lasotuvi_django_me.egg-info/PKG-INFO
lasotuvi_django_me.egg-info/SOURCES.txt
lasotuvi_django_me.egg-info/dependency_links.txt
lasotuvi_django_me.egg-info/not-zip-safe
lasotuvi_django_me.egg-info/requires.txt
lasotuvi_django_me.egg-info/top_level.txt