Metadata-Version: 2.1
Name: lasotuvi-django-me
Version: 0.1.3
Summary: Chương trình an sao tử vi mã nguồn mở sử dụng django
Home-page: https://github.com/tuangit/lasotuvi-django-me
Author: doanguyen
Author-email: dungnv2410@gmail.com
License: MIT
Platform: UNKNOWN
